pdf2-0.2.1.dist-info/METADATA
pdf2-0.2.1.dist-info/WHEEL
pdf2-0.2.1.dist-info/licenses/LICENSE
pdf2/__init__.py
pdf2/_core.pyi
pdf2/generator.rs
pdf2/parser.rs
pdf2/pdf2.cpython-39-aarch64-linux-gnu.so
pdf2/py.typed
pdf2/structure.rs
pdf2/test_generator.rs
pdf2/test_parser.rs
pdf2/test_structure.rs
pdf2-0.2.1.dist-info/RECORD
